armstrongnbrfinder/__init__.py
Armstrongnumberfinder-3.1.1.dist-info/METADATA
Armstrongnumberfinder-3.1.1.dist-info/WHEEL
Armstrongnumberfinder-3.1.1.dist-info/license
Armstrongnumberfinder-3.1.1.dist-info/top_level.txt
Armstrongnumberfinder-3.1.1.dist-info/RECORD
