Metadata-Version: 2.1
Name: Armstrongnumberfinder
Version: 3.1.1
Summary: This package allows you to find armstrong number
Home-page: UNKNOWN
Author: Shourjjo Majumder
Author-email: contact@shourgamer2.tk
License: UNKNOWN
Platform: UNKNOWN
License-File: license
